ara_api/__init__.py
ara_api/__main__.py
ara_api/_core/__init__.py
ara_api/_core/manager.py
ara_api/_core/processors/__init__.py
ara_api/_core/processors/msp_processor.py
ara_api/_core/processors/nav_processor.py
ara_api/_core/processors/vision_processor.py
ara_api/_core/services/__init__.py
ara_api/_core/services/analyzer/__init__.py
ara_api/_core/services/analyzer/app.py
ara_api/_core/services/analyzer/controller/__init__.py
ara_api/_core/services/analyzer/controller/offline_controller.py
ara_api/_core/services/analyzer/controller/online_controller.py
ara_api/_core/services/analyzer/pages/__init__.py
ara_api/_core/services/analyzer/pages/accel_pages.py
ara_api/_core/services/analyzer/pages/analog_pages.py
ara_api/_core/services/analyzer/pages/freq_pages.py
ara_api/_core/services/analyzer/pages/gyro_pages.py
ara_api/_core/services/analyzer/pages/motor_pages.py
ara_api/_core/services/msp/__init__.py
ara_api/_core/services/msp/connection/__init__.py
ara_api/_core/services/msp/connection/connection_manager.py
ara_api/_core/services/msp/controller/__init__.py
ara_api/_core/services/msp/controller/msp_commands.py
ara_api/_core/services/msp/controller/msp_controller.py
ara_api/_core/services/msp/controller/protocol/__init__.py
ara_api/_core/services/msp/controller/protocol/checksum.py
ara_api/_core/services/msp/controller/protocol/constants.py
ara_api/_core/services/msp/controller/protocol/decoder.py
ara_api/_core/services/msp/controller/protocol/encoder.py
ara_api/_core/services/msp/controller/state/__init__.py
ara_api/_core/services/msp/controller/state/fc_config.py
ara_api/_core/services/msp/controller/state/gps_data.py
ara_api/_core/services/msp/controller/state/sensor_data.py
ara_api/_core/services/msp/msp_service.py
ara_api/_core/services/msp/telemetry/__init__.py
ara_api/_core/services/msp/telemetry/readers/__init__.py
ara_api/_core/services/msp/telemetry/readers/altitude_reader.py
ara_api/_core/services/msp/telemetry/readers/analog_reader.py
ara_api-1.1.0rc2.dist-info/METADATA
ara_api-1.1.0rc2.dist-info/WHEEL
ara_api-1.1.0rc2.dist-info/entry_points.txt
ara_api-1.1.0rc2.dist-info/licenses/LICENSE
ara_api-1.1.0rc2.dist-info/RECORD
