Metadata-Version: 2.4
Name: ara-api
Version: 1.1.0rc2
Summary: Applied Robotics Avia API for ARA MINI, ARA EDU and ARA FPV drones
License: MIT License
License-File: LICENSE
Keywords: robotics,drones,API,ARA
Author: Alexander Kleimenov
Maintainer: Alexander Kleimenov
Maintainer-email: nequamy@gmail.com
Requires-Python: >=3.8
Classifier: Development Status :: 2 - Pre-Alpha
Classifier: Intended Audience :: Developers
Classifier: License :: OSI Approved :: MIT License
Classifier: Programming Language :: Python
Classifier: Programming Language :: Python :: 3
Classifier: Programming Language :: Python :: 3.8
Classifier: Programming Language :: Python :: 3.9
Classifier: Programming Language :: Python :: 3.10
Classifier: Programming Language :: Python :: 3.11
Classifier: Programming Language :: Python :: 3.12
Classifier: Programming Language :: Python :: 3.13
Classifier: Topic :: Software Development
Classifier: Topic :: Scientific/Engineering
Classifier: Operating System :: Unix
Classifier: Operating System :: MacOS
Classifier: Operating System :: Microsoft :: Windows
Requires-Dist: colorama (==0.4.6)
Requires-Dist: customtkinter (==5.2.2)
Requires-Dist: fastapi (>=0.100.0,<0.122.0) ; python_version < "3.9"
Requires-Dist: fastapi (>=0.121.1,<0.122.0) ; python_version >= "3.9"
Requires-Dist: grpcio (==1.69.0)
Requires-Dist: grpcio-tools (==1.66.2)
Requires-Dist: numpy (>=1.24.0,<1.25.0) ; python_version == "3.8"
Requires-Dist: numpy (>=1.26.0,<2.0.0) ; python_version == "3.9"
Requires-Dist: numpy (>=2.1.0,<3.0.0) ; python_version >= "3.10"
Requires-Dist: opencv-contrib-python (==4.10.0.84)
Requires-Dist: opencv-python (==4.10.0.84)
Requires-Dist: pandas (>=2.0.0,<2.1.0) ; python_version == "3.8"
Requires-Dist: pandas (>=2.2.0,<3.0.0) ; python_version >= "3.9"
Requires-Dist: pillow (>=10.0.0,<11.0.0) ; python_version < "3.10"
Requires-Dist: pillow (>=11.0.0,<12.0.0) ; python_version >= "3.10"
Requires-Dist: pydantic (>=2.0.0,<2.6.0) ; python_version == "3.8"
Requires-Dist: pydantic (>=2.5.0,<2.11.0) ; python_version == "3.9"
Requires-Dist: pydantic (>=2.8.0,<3.0.0) ; python_version >= "3.10"
Requires-Dist: pyfiglet (>=0.8.0,<1.0.0)
Requires-Dist: pyserial (==3.5)
Requires-Dist: requests (==2.32.3)
Requires-Dist: rich (>=14.0.0,<15.0.0)
Requires-Dist: scipy (>=1.10.0,<1.11.0) ; python_version == "3.8"
Requires-Dist: scipy (>=1.13.0,<1.14.0) ; python_version == "3.9"
Requires-Dist: scipy (>=1.14.0,<2.0.0) ; python_version >= "3.10"
Requires-Dist: uvicorn (>=0.20.0,<0.28.0) ; python_version == "3.8"
Requires-Dist: uvicorn (>=0.30.0,<0.40.0) ; python_version >= "3.9"
